kartaview_tools/__init__.py
kartaview_tools/api10.py
kartaview_tools/api20.py
kartaview_tools/catmull_rom.py
kartaview_tools/gpsfix.py
kartaview_tools/kv_auth.py
kartaview_tools/kv_sequence.py
kartaview_tools/kv_upload.py
kartaview_tools/kv_vantrue_x4s.py
kartaview_tools/mp4.py
kartaview_tools-0.0.5.dist-info/LICENSE
kartaview_tools-0.0.5.dist-info/METADATA
kartaview_tools-0.0.5.dist-info/WHEEL
kartaview_tools-0.0.5.dist-info/entry_points.txt
kartaview_tools-0.0.5.dist-info/top_level.txt
kartaview_tools-0.0.5.dist-info/RECORD
