Metadata-Version: 2.1
Name: kartaview-tools
Version: 0.0.5
Summary: Commandline Image Uploader for KartaView
Home-page: https://github.com/MarcelloPerathoner/kartaview-tools
Author: Marcello Perathoner
Author-email: marcello@perathoner.de
Project-URL: Bug Tracker, https://github.com/MarcelloPerathoner/kartaview-tools/issues
Keywords: kartaview,commandline,console,image,upload
Classifier: Development Status :: 3 - Alpha
Classifier: Environment :: Console
Classifier: Intended Audience :: End Users/Desktop
Classifier: License :: OSI Approved :: GNU General Public License v3 or later (GPLv3+)
Classifier: Operating System :: POSIX :: Linux
Classifier: Programming Language :: Python :: 3 :: Only
Classifier: Topic :: Utilities
Requires-Python: >=3.10.4
License-File: LICENSE
